<?xml version="1.0" encoding="UTF-8"?>
<beans xmlns="http://www.springframework.org/schema/beans"
  xmlns:xsi="http://www.w3.org/2001/XMLSchema-instance"
  xmlns:util="http://www.springframework.org/schema/util"
  xsi:schemaLocation="    
    http://www.springframework.org/schema/beans http://www.springframework.org/schema/beans/spring-beans-2.5.xsd
    http://www.springframework.org/schema/util http://www.springframework.org/schema/util/spring-util-2.5.xsd"
  default-lazy-init="true">

  <util:map id="configurationServiceSql">
    <entry key="selectDataEventActionsByIdSql">
      <value>
        select data_event_action from $[sym.sync.table.prefix]_node_group_link where
        source_node_group_id = ? and target_node_group_id = ?
      </value>
    </entry>
    <entry key="groupsLinksSql">
      <value>
        select source_node_group_id, target_node_group_id, data_event_action from
        $[sym.sync.table.prefix]_node_group_link
      </value>
    </entry>
    <entry key="groupsLinksForSql">
      <value>
        select source_node_group_id, target_node_group_id, data_event_action from
        $[sym.sync.table.prefix]_node_group_link where source_node_group_id = ?
      </value>
    </entry>
    <entry key="selectChannelsSql">
      <value>
        select c.channel_id, n.node_id, nc.ignore_enabled, nc.suspend_enabled, c.processing_order,
        c.max_batch_size, c.enabled, c.max_batch_to_send, c.batch_algorithm from $[sym.sync.table.prefix]_channel c inner
        join $[sym.sync.table.prefix]_node_identity n on 1 = 1 left outer join
        $[sym.sync.table.prefix]_node_channel_ctl nc on c.channel_id = nc.channel_id and n.node_id =
        nc.node_id order by c.processing_order asc, c.channel_id
      </value>
    </entry>
    <entry key="insertChannelSql">
      <value>
        insert into $[sym.sync.table.prefix]_channel (channel_id, processing_order, max_batch_size,
        max_batch_to_send, enabled, batch_algorithm, description) values (?, ?, ?, ?, ?, ?, null)
      </value>
    </entry>
    <entry key="updateChannelSql">
      <value>
        update $[sym.sync.table.prefix]_channel set processing_order=?, max_batch_size=?,
        max_batch_to_send=?, enabled=?, batch_algorithm=? where channel_id=?
      </value>
    </entry>
    <entry key="deleteChannelSql">
      <value>delete from $[sym.sync.table.prefix]_channel where channel_id=?</value>
    </entry>
  </util:map>

</beans>